legendastv/__init__.py
legendastv-0.1.8.dist-info/LICENSE
legendastv-0.1.8.dist-info/METADATA
legendastv-0.1.8.dist-info/WHEEL
legendastv-0.1.8.dist-info/top_level.txt
legendastv-0.1.8.dist-info/RECORD
