Metadata-Version: 2.1
Name: legendastv
Version: 0.1.8
Summary: Library to automate downloads from Legendas TV website
Home-page: https://github.com/vinigfer/legendastv
Author: Vinicius Gubiani Ferreira
Author-email: vini.g.fer@gmail.com
License: MIT
Platform: UNKNOWN
Classifier: Programming Language :: Python :: 3
Classifier: Programming Language :: Python :: 3.6
Requires-Dist: beautifulsoup4
Requires-Dist: requests
